inscar/__init__.py
inscar/config.py
inscar/integrand_functions.py
inscar/numba_integration.py
inscar/spectrum_calculation.py
inscar/vdfs.py
inscar/experimental/extra_vdfs.py
inscar-3.3.2.dist-info/METADATA
inscar-3.3.2.dist-info/WHEEL
inscar-3.3.2.dist-info/licenses/LICENSE.rst
inscar-3.3.2.dist-info/RECORD
