Metadata-Version: 2.3
Name: inscar
Version: 3.3.2
Summary: Calculate an incoherent scatter spectrum with arbitrary isotropic electron velocity distributions and radar pointing at oblique angles to the magnetic field
Project-URL: changelog, https://github.com/engeir/inscar/releases
Project-URL: homepage, https://github.com/engeir/inscar
Project-URL: repository, https://github.com/engeir/inscar
Project-URL: documentation, https://inscar.readthedocs.io
Author-email: Eirik Enger <engeir@pm.me>
License-File: LICENSE.rst
Classifier: Development Status :: 5 - Production/Stable
Classifier: Programming Language :: Python :: 3.9
Classifier: Programming Language :: Python :: 3.10
Classifier: Programming Language :: Python :: 3.11
Classifier: Programming Language :: Python :: 3.12
Requires-Python: >=3.9
Requires-Dist: attrs>=23.2.0
Requires-Dist: contourpy>=1.1.1
Requires-Dist: numba>=0.58.1
Requires-Dist: numpy>=2.0.0
Requires-Dist: scipy>=1.10.1
